djot/__init__.py
djot-0.0.1.dist-info/METADATA
djot-0.0.1.dist-info/WHEEL
djot-0.0.1.dist-info/licenses/LICENSE
djot-0.0.1.dist-info/RECORD
