Metadata-Version: 2.3
Name: djot
Version: 0.0.1
Summary: A parser and HTML converter for djot markup.
Project-URL: Homepage, https://codeberg.org/crmsnbleyd/djot.py
Project-URL: Repository, https://codeberg.org/crmsnbleyd/djot.py.git
Author-email: Drew Jose <mail@drewsh.com>
License: As a special exception to the GNU Lesser General Public License version 3
License-File: LICENSE
Classifier: License :: OSI Approved :: GNU Lesser General Public License v3 or later (LGPLv3+)
Classifier: Topic :: Text Processing :: Markup
